JiqiZhixin2019GaofenJiaochengYouzhiJiaocaiKecheng/README.md
JiqiZhixin2019GaofenJiaochengYouzhiJiaocaiKecheng/__init__.py
JiqiZhixin2019GaofenJiaochengYouzhiJiaocaiKecheng/__main__.py
JiqiZhixin2019GaofenJiaochengYouzhiJiaocaiKecheng/file.epub
JiqiZhixin2019GaofenJiaochengYouzhiJiaocaiKecheng/index.html
JiqiZhixin2019GaofenJiaochengYouzhiJiaocaiKecheng/css/__init__.py
JiqiZhixin2019GaofenJiaochengYouzhiJiaocaiKecheng/css/annotations.css
JiqiZhixin2019GaofenJiaochengYouzhiJiaocaiKecheng/css/main.css
JiqiZhixin2019GaofenJiaochengYouzhiJiaocaiKecheng/css/normalize.css
JiqiZhixin2019GaofenJiaochengYouzhiJiaocaiKecheng/css/popup.css
JiqiZhixin2019GaofenJiaochengYouzhiJiaocaiKecheng/font/__init__.py
JiqiZhixin2019GaofenJiaochengYouzhiJiaocaiKecheng/font/fontello.eot
JiqiZhixin2019GaofenJiaochengYouzhiJiaocaiKecheng/font/fontello.svg
JiqiZhixin2019GaofenJiaochengYouzhiJiaocaiKecheng/font/fontello.ttf
JiqiZhixin2019GaofenJiaochengYouzhiJiaocaiKecheng/font/fontello.woff
JiqiZhixin2019GaofenJiaochengYouzhiJiaocaiKecheng/img/__init__.py
JiqiZhixin2019GaofenJiaochengYouzhiJiaocaiKecheng/img/annotator-glyph-sprite.png
JiqiZhixin2019GaofenJiaochengYouzhiJiaocaiKecheng/img/annotator-icon-sprite.png
JiqiZhixin2019GaofenJiaochengYouzhiJiaocaiKecheng/img/apple-touch-icon.png
JiqiZhixin2019GaofenJiaochengYouzhiJiaocaiKecheng/img/cancelfullscreen.png
JiqiZhixin2019GaofenJiaochengYouzhiJiaocaiKecheng/img/close.png
JiqiZhixin2019GaofenJiaochengYouzhiJiaocaiKecheng/img/fullscreen.png
JiqiZhixin2019GaofenJiaochengYouzhiJiaocaiKecheng/img/loader.gif
JiqiZhixin2019GaofenJiaochengYouzhiJiaocaiKecheng/img/menu-icon.png
JiqiZhixin2019GaofenJiaochengYouzhiJiaocaiKecheng/img/save.png
JiqiZhixin2019GaofenJiaochengYouzhiJiaocaiKecheng/img/saved.png
JiqiZhixin2019GaofenJiaochengYouzhiJiaocaiKecheng/img/settings-s.png
JiqiZhixin2019GaofenJiaochengYouzhiJiaocaiKecheng/img/settings.png
JiqiZhixin2019GaofenJiaochengYouzhiJiaocaiKecheng/img/star.png
jiqi_zhixin_2019_gaofen_jiaocheng_youzhi_jiaocai_kecheng-2024.3.5.0.dist-info/METADATA
jiqi_zhixin_2019_gaofen_jiaocheng_youzhi_jiaocai_kecheng-2024.3.5.0.dist-info/WHEEL
jiqi_zhixin_2019_gaofen_jiaocheng_youzhi_jiaocai_kecheng-2024.3.5.0.dist-info/entry_points.txt
jiqi_zhixin_2019_gaofen_jiaocheng_youzhi_jiaocai_kecheng-2024.3.5.0.dist-info/top_level.txt
jiqi_zhixin_2019_gaofen_jiaocheng_youzhi_jiaocai_kecheng-2024.3.5.0.dist-info/RECORD
